{
  "1001": {
    "name": "March 7th",
    "weapons": [
      "23005",
      "21002",
      "24002"
    ],
    "subStats": [
      "SPD",
      "Effect Hit Rate",
      "DEF",
      "Effect RES",
      "HP"
    ],
    "stats": {
      "BaseSpeed": "134+",
      "CriticalChance": "5%",
      "CriticalDamage": "50%",
      "SPRatio": "119%",
      "StatusProbabilityBase": "117%",
      "BreakDamageAddedRatioBase": "0%"
    },
    "version": "2.0",
    "sets": [
      [
        "304",
        "310"
      ],
      [
        "103"
      ],
      [
        "103",
        "114"
      ]
    ],
    "mainStats": {
      "HEAD": "HP",
      "HAND": "ATK",
      "BODY": [
        "EHR%",
        "DEF%"
      ],
      "FOOT": [
        "SPD"
      ],
      "NECK": [
        "DEF%"
      ],
      "OBJECT": [
        "Energy",
        "DEF%"
      ]
    },
    "eidolon": "100106",
    "talents": "13",
    "synergies": [
      "1302",
      "1107",
      "1003",
      "1204",
      "1102",
      "1008",
      "1013",
      "1106"
    ]
  },
  "1002": {
    "name": "Dan Heng",
    "weapons": [
      "23001",
      "21010",
      "24001"
    ],
    "subStats": [
      "CRIT DMG",
      "CRIT Rate",
      "ATK",
      "SPD"
    ],
    "stats": {
      "BaseSpeed": "134+",
      "CriticalChance": "70%",
      "CriticalDamage": "140%",
      "SPRatio": "100%",
      "StatusProbabilityBase": "0%",
      "BreakDamageAddedRatioBase": "0%"
    },
    "version": "2.0",
    "sets": [
      [
        "311",
        "309"
      ],
      [
        "110",
        "102"
      ],
      [
        "102"
      ]
    ],
    "mainStats": {
      "HEAD": "HP",
      "HAND": "ATK",
      "BODY": [
        "Crit DMG / Rate"
      ],
      "FOOT": [
        "SPD"
      ],
      "NECK": [
        "Wind DMG"
      ],
      "OBJECT": [
        "ATK%"
      ]
    },
    "eidolon": "100204",
    "talents": "3",
    "synergies": [
      "1101",
      "1208",
      "1217",
      "1203",
      "1006",
      "1306",
      "1215",
      "1202"
    ]
  },
  "1003": {
    "name": "Himeko",
    "weapons": [
      "23010",
      "23028",
      "21020"
    ],
    "subStats": [
      "CRIT DMG",
      "CRIT Rate",
      "ATK",
      "SPD"
    ],
    "stats": {
      "BaseSpeed": "121/134",
      "CriticalChance": "70%",
      "CriticalDamage": "140%",
      "SPRatio": "100%",
      "StatusProbabilityBase": "0%",
      "BreakDamageAddedRatioBase": "0%"
    },
    "version": "2.3",
    "sets": [
      [
        "315",
        "306"
      ],
      [
        "115"
      ],
      [
        "120"
      ]
    ],
    "mainStats": {
      "HEAD": "HP",
      "HAND": "ATK",
      "BODY": [
        "Crit DMG / Rate"
      ],
      "FOOT": [
        "SPD",
        "ATK%"
      ],
      "NECK": [
        "Fire DMG"
      ],
      "OBJECT": [
        "ATK%"
      ]
    },
    "eidolon": "100304",
    "talents": "1",
    "synergies": [
      "1217",
      "1314",
      "1304",
      "1309",
      "1303",
      "1112",
      "1013",
      "1202"
    ]
  },
  "1004": {
    "name": "Welt",
    "weapons": [
      "23007",
      "23004",
      "21001"
    ],
    "subStats": [
      "SPD",
      "Effect Hit Rate",
      "CRIT DMG",
      "CRIT Rate",
      "ATK"
    ],
    "stats": {
      "BaseSpeed": "134+",
      "CriticalChance": "70%",
      "CriticalDamage": "140%",
      "SPRatio": "119%/100%",
      "StatusProbabilityBase": "40%",
      "BreakDamageAddedRatioBase": "0%"
    },
    "version": "2.3",
    "sets": [
      [
        "303",
        "311"
      ],
      [
        "117"
      ],
      [
        "112"
      ]
    ],
    "mainStats": {
      "HEAD": "HP",
      "HAND": "ATK",
      "BODY": [
        "Crit DMG / Rate"
      ],
      "FOOT": [
        "SPD"
      ],
      "NECK": [
        "Imaginary DMG",
        "ATK%"
      ],
      "OBJECT": [
        "Energy",
        "ATK%"
      ]
    },
    "eidolon": "100404",
    "talents": "15",
    "synergies": [
      "1308",
      "1304",
      "1205",
      "1208",
      "1217",
      "1303",
      "1006",
      "1306"
    ]
  },
  "1005": {
    "name": "Kafka",
    "weapons": [
      "23006",
      "21001",
      "23007"
    ],
    "subStats": [
      "SPD",
      "ATK",
      "Effect Hit Rate",
      "Break Effect"
    ],
    "stats": {
      "BaseSpeed": "143+",
      "CriticalChance": "5%",
      "CriticalDamage": "50%",
      "SPRatio": "100%",
      "StatusProbabilityBase": "29%",
      "BreakDamageAddedRatioBase": "0%"
    },
    "version": "2.3",
    "sets": [
      [
        "311",
        "301"
      ],
      [
        "116"
      ],
      [
        "109"
      ]
    ],
    "mainStats": {
      "HEAD": "HP",
      "HAND": "ATK",
      "BODY": [
        "ATK%"
      ],
      "FOOT": [
        "SPD",
        "ATK%"
      ],
      "NECK": [
        "Lightning DMG",
        "ATK%"
      ],
      "OBJECT": [
        "ATK%"
      ]
    },
    "eidolon": "100501",
    "talents": "3",
    "synergies": [
      "1308",
      "1304",
      "1307",
      "1217",
      "1309",
      "1303",
      "1009",
      "1301"
    ]
  },
  "1006": {
    "name": "Silver Wolf",
    "weapons": [
      "22000",
      "23007",
      "21015"
    ],
    "subStats": [
      "Effect Hit Rate",
      "SPD",
      "HP",
      "DEF",
      "Effect RES",
      "Break Effect"
    ],
    "stats": {
      "BaseSpeed": "143+",
      "CriticalChance": "5%",
      "CriticalDamage": "50%",
      "SPRatio": "119%",
      "StatusProbabilityBase": "96%/47%",
      "BreakDamageAddedRatioBase": "0%"
    },
    "version": "2.3",
    "sets": [
      [
        "312",
        "310"
      ],
      [
        "113",
        "114"
      ],
      [
        "110"
      ]
    ],
    "mainStats": {
      "HEAD": "HP",
      "HAND": "ATK",
      "BODY": [
        "EHR%",
        "HP%",
        "DEF%"
      ],
      "FOOT": [
        "SPD"
      ],
      "NECK": [
        "HP%",
        "DEF%",
        "Quantum DMG"
      ],
      "OBJECT": [
        "Energy"
      ]
    },
    "eidolon": "100602",
    "talents": "3",
    "synergies": [
      "1308",
      "1305",
      "1208",
      "1314",
      "1212",
      "1102",
      "1306",
      "1201",
      "1214"
    ]
  },
  "1008": {
    "name": "Arlan",
    "weapons": [
      "23009",
      "24000",
      "21012"
    ],
    "subStats": [
      "SPD",
      "CRIT DMG",
      "CRIT Rate",
      "ATK"
    ],
    "stats": {
      "BaseSpeed": "134",
      "CriticalChance": "70%",
      "CriticalDamage": "140%",
      "SPRatio": "100%",
      "StatusProbabilityBase": "0%",
      "BreakDamageAddedRatioBase": "0%"
    },
    "version": "2.3",
    "sets": [
      [
        "309",
        "311"
      ],
      [
        "109"
      ],
      [
        "113"
      ]
    ],
    "mainStats": {
      "HEAD": "HP",
      "HAND": "ATK",
      "BODY": [
        "Crit DMG / Rate"
      ],
      "FOOT": [
        "SPD"
      ],
      "NECK": [
        "Lightning DMG"
      ],
      "OBJECT": [
        "ATK%"
      ]
    },
    "eidolon": "100806",
    "talents": "13",
    "synergies": [
      "1304",
      "1101",
      "1208",
      "1303",
      "1006",
      "1306",
      "1106",
      "1202"
    ]
  },
  "1009": {
    "name": "Asta",
    "weapons": [
      "20012",
      "21004",
      "21011"
    ],
    "subStats": [
      "SPD",
      "HP",
      "DEF",
      "Effect RES",
      "Break Effect"
    ],
    "stats": {
      "BaseSpeed": "134+",
      "CriticalChance": "5%",
      "CriticalDamage": "50%",
      "SPRatio": "119%",
      "StatusProbabilityBase": "0%",
      "BreakDamageAddedRatioBase": "0%"
    },
    "version": "2.3",
    "sets": [
      [
        "310",
        "312"
      ],
      [
        "114"
      ],
      [
        "118"
      ]
    ],
    "mainStats": {
      "HEAD": "HP",
      "HAND": "ATK",
      "BODY": [
        "HP%",
        "DEF%"
      ],
      "FOOT": [
        "SPD"
      ],
      "NECK": [
        "HP%",
        "DEF%"
      ],
      "OBJECT": [
        "Energy"
      ]
    },
    "eidolon": "100906",
    "talents": "1",
    "synergies": [
      "1307",
      "1310",
      "1003",
      "1204",
      "1005",
      "1102",
      "1112",
      "1109"
    ]
  },
  "1013": {
    "name": "Herta",
    "weapons": [
      "23010",
      "23028",
      "21020"
    ],
    "subStats": [
      "CRIT DMG",
      "CRIT Rate",
      "ATK",
      "SPD"
    ],
    "stats": {
      "BaseSpeed": "100/134+",
      "CriticalChance": "70%",
      "CriticalDamage": "140%",
      "SPRatio": "100%",
      "StatusProbabilityBase": "0%",
      "BreakDamageAddedRatioBase": "0%"
    },
    "version": "2.3",
    "sets": [
      [
        "315",
        "306"
      ],
      [
        "115"
      ],
      [
        "120"
      ]
    ],
    "mainStats": {
      "HEAD": "HP",
      "HAND": "ATK",
      "BODY": [
        "Crit DMG / Rate"
      ],
      "FOOT": [
        "ATK%",
        "SPD"
      ],
      "NECK": [
        "Ice DMG"
      ],
      "OBJECT": [
        "ATK%"
      ]
    },
    "eidolon": "101306",
    "talents": "1",
    "synergies": [
      "1304",
      "1107",
      "1003",
      "1217",
      "1314",
      "1309",
      "1303",
      "1106"
    ]
  },
  "1101": {
    "name": "Bronya",
    "weapons": [
      "23003",
      "21025",
      "21011"
    ],
    "subStats": [
      "SPD",
      "CRIT DMG",
      "HP",
      "DEF",
      "Effect RES"
    ],
    "stats": {
      "BaseSpeed": "134/161",
      "CriticalChance": "5%",
      "CriticalDamage": "200%",
      "SPRatio": "119%",
      "StatusProbabilityBase": "0%",
      "BreakDamageAddedRatioBase": "0%"
    },
    "version": "2.3",
    "sets": [
      [
        "310",
        "302"
      ],
      [
        "106",
        "114"
      ],
      [
        "114"
      ]
    ],
    "mainStats": {
      "HEAD": "HP",
      "HAND": "ATK",
      "BODY": [
        "Crit DMG"
      ],
      "FOOT": [
        "SPD"
      ],
      "NECK": [
        "HP%",
        "DEF%"
      ],
      "OBJECT": [
        "Energy"
      ]
    },
    "eidolon": "110101",
    "talents": "3",
    "synergies": [
      "1308",
      "1302",
      "1205",
      "1315",
      "1213",
      "1003",
      "1212",
      "1102"
    ]
  },
  "1102": {
    "name": "Seele",
    "weapons": [
      "23001",
      "21010",
      "24001"
    ],
    "subStats": [
      "CRIT DMG",
      "CRIT Rate",
      "ATK",
      "SPD"
    ],
    "stats": {
      "BaseSpeed": "121/132",
      "CriticalChance": "70%",
      "CriticalDamage": "140%",
      "SPRatio": "100%",
      "StatusProbabilityBase": "0%",
      "BreakDamageAddedRatioBase": "0%"
    },
    "version": "2.0",
    "sets": [
      [
        "309",
        "311"
      ],
      [
        "108"
      ],
      [
        "108",
        "102"
      ]
    ],
    "mainStats": {
      "HEAD": "HP",
      "HAND": "ATK",
      "BODY": [
        "Crit DMG / Rate"
      ],
      "FOOT": [
        "ATK%"
      ],
      "NECK": [
        "Quantum DMG"
      ],
      "OBJECT": [
        "ATK%"
      ]
    },
    "eidolon": "110202",
    "talents": "13",
    "synergies": [
      "1101",
      "1208",
      "1217",
      "1203",
      "1006",
      "1306",
      "1215",
      "1202"
    ]
  },
  "1103": {
    "name": "Serval",
    "weapons": [
      "23010",
      "23000",
      "21027"
    ],
    "subStats": [
      "CRIT DMG",
      "CRIT Rate",
      "ATK",
      "SPD"
    ],
    "stats": {
      "BaseSpeed": "134+",
      "CriticalChance": "70%",
      "CriticalDamage": "140%",
      "SPRatio": "100%",
      "StatusProbabilityBase": "0%",
      "BreakDamageAddedRatioBase": "0%"
    },
    "version": "2.0",
    "sets": [
      [
        "309",
        "311"
      ],
      [
        "116"
      ],
      [
        "109"
      ]
    ],
    "mainStats": {
      "HEAD": "HP",
      "HAND": "ATK",
      "BODY": [
        "Crit DMG / Rate"
      ],
      "FOOT": [
        "SPD"
      ],
      "NECK": [
        "Lightning DMG"
      ],
      "OBJECT": [
        "ATK%"
      ]
    },
    "eidolon": "110306",
    "talents": "3",
    "synergies": [
      "1307",
      "1208",
      "1217",
      "1005",
      "1303",
      "1009",
      "1106",
      "1202"
    ]
  },
  "1104": {
    "name": "Gepard",
    "weapons": [
      "23005",
      "21009",
      "21002"
    ],
    "subStats": [
      "SPD",
      "DEF",
      "Effect RES",
      "HP"
    ],
    "stats": {
      "BaseSpeed": "134+",
      "CriticalChance": "5%",
      "CriticalDamage": "50%",
      "SPRatio": "119%",
      "StatusProbabilityBase": "0%",
      "BreakDamageAddedRatioBase": "0%"
    },
    "version": "2.0",
    "sets": [
      [
        "310",
        "302"
      ],
      [
        "103"
      ],
      [
        "103",
        "114"
      ]
    ],
    "mainStats": {
      "HEAD": "HP",
      "HAND": "ATK",
      "BODY": [
        "DEF%"
      ],
      "FOOT": [
        "SPD"
      ],
      "NECK": [
        "DEF%"
      ],
      "OBJECT": [
        "Energy"
      ]
    },
    "eidolon": "110404",
    "talents": "3",
    "synergies": [
      "1302",
      "1305",
      "1003",
      "1204",
      "1209",
      "1008",
      "1013",
      "1109"
    ]
  },
  "1105": {
    "name": "Natasha",
    "weapons": [
      "23017",
      "23013",
      "21000"
    ],
    "subStats": [
      "SPD",
      "HP",
      "Effect RES",
      "DEF"
    ],
    "stats": {
      "BaseSpeed": "143+",
      "CriticalChance": "5%",
      "CriticalDamage": "50%",
      "SPRatio": "119%",
      "StatusProbabilityBase": "0%",
      "BreakDamageAddedRatioBase": "0%",
      "HealRatio": "34.56%"
    },
    "version": "2.0",
    "sets": [
      [
        "310",
        "302"
      ],
      [
        "114"
      ],
      [
        "101"
      ]
    ],
    "mainStats": {
      "HEAD": "HP",
      "HAND": "ATK",
      "BODY": [
        "OHB%"
      ],
      "FOOT": [
        "SPD"
      ],
      "NECK": [
        "HP%"
      ],
      "OBJECT": [
        "Energy"
      ]
    },
    "eidolon": "110502",
    "talents": "3",
    "synergies": [
      "1302",
      "1205",
      "1107",
      "1213",
      "1204",
      "1212",
      "1005",
      "1102"
    ]
  },
  "1106": {
    "name": "Pela",
    "weapons": [
      "22000",
      "21015",
      "21008"
    ],
    "subStats": [
      "Effect Hit Rate",
      "HP",
      "DEF",
      "SPD",
      "Effect RES"
    ],
    "stats": {
      "BaseSpeed": "143+",
      "CriticalChance": "5%",
      "CriticalDamage": "50%",
      "SPRatio": "119%",
      "StatusProbabilityBase": "67%",
      "BreakDamageAddedRatioBase": "0%"
    },
    "version": "2.3",
    "sets": [
      [
        "310",
        "302"
      ],
      [
        "114",
        "113"
      ],
      [
        "110"
      ]
    ],
    "mainStats": {
      "HEAD": "HP",
      "HAND": "ATK",
      "BODY": [
        "EHR%",
        "HP%",
        "DEF%"
      ],
      "FOOT": [
        "SPD"
      ],
      "NECK": [
        "HP%",
        "DEF%"
      ],
      "OBJECT": [
        "Energy"
      ]
    },
    "eidolon": "110606",
    "talents": "1",
    "synergies": [
      "1308",
      "1305",
      "1212",
      "1213",
      "1217",
      "1005",
      "1107",
      "1312"
    ]
  },
  "1107": {
    "name": "Clara",
    "weapons": [
      "23015",
      "24000",
      "23002"
    ],
    "subStats": [
      "CRIT DMG",
      "CRIT Rate",
      "ATK",
      "Break Effect",
      "Effect RES"
    ],
    "stats": {
      "BaseSpeed": "96",
      "CriticalChance": "70%",
      "CriticalDamage": "140%",
      "SPRatio": "100%",
      "StatusProbabilityBase": "0%",
      "BreakDamageAddedRatioBase": "0%"
    },
    "version": "2.3",
    "sets": [
      [
        "315",
        "306"
      ],
      [
        "105"
      ],
      [
        "113"
      ]
    ],
    "mainStats": {
      "HEAD": "HP",
      "HAND": "ATK",
      "BODY": [
        "Crit DMG / Rate"
      ],
      "FOOT": [
        "ATK%"
      ],
      "NECK": [
        "Physical DMG"
      ],
      "OBJECT": [
        "ATK%"
      ]
    },
    "eidolon": "110706",
    "talents": "1",
    "synergies": [
      "1304",
      "1217",
      "1203",
      "1309",
      "1303",
      "1102",
      "1112",
      "1202"
    ]
  },
  "1109": {
    "name": "Hook",
    "weapons": [
      "21026",
      "24000",
      "23009"
    ],
    "subStats": [
      "CRIT DMG",
      "CRIT Rate",
      "ATK",
      "SPD"
    ],
    "stats": {
      "BaseSpeed": "121/134+",
      "CriticalChance": "70%",
      "CriticalDamage": "140%",
      "SPRatio": "100%",
      "StatusProbabilityBase": "0%",
      "BreakDamageAddedRatioBase": "0%",
      "HealRatio": "0%"
    },
    "version": "2.0",
    "sets": [
      [
        "309",
        "311"
      ],
      [
        "116"
      ],
      [
        "107",
        "102"
      ]
    ],
    "mainStats": {
      "HEAD": "HP",
      "HAND": "ATK",
      "BODY": [
        "Crit DMG / Rate"
      ],
      "FOOT": [
        "SPD",
        "ATK%"
      ],
      "NECK": [
        "Fire DMG"
      ],
      "OBJECT": [
        "ATK%"
      ]
    },
    "eidolon": "110906",
    "talents": "13",
    "synergies": [
      "1101",
      "1208",
      "1217",
      "1303",
      "1006",
      "1306",
      "1009",
      "1210"
    ]
  },
  "1112": {
    "name": "Topaz & Numby",
    "weapons": [
      "23016",
      "24001",
      "21010"
    ],
    "subStats": [
      "CRIT DMG",
      "CRIT Rate",
      "ATK",
      "SPD"
    ],
    "stats": {
      "BaseSpeed": "143+",
      "CriticalChance": "70%",
      "CriticalDamage": "140%",
      "SPRatio": "100%",
      "StatusProbabilityBase": "0%",
      "BreakDamageAddedRatioBase": "0"
    },
    "sets": [
      [
        "306",
        "311"
      ],
      [
        "115"
      ],
      [
        "107",
        "115"
      ]
    ],
    "mainStats": {
      "HEAD": "HP",
      "HAND": "ATK",
      "BODY": [
        "Crit DMG / Rate"
      ],
      "FOOT": [
        "SPD",
        "ATK%"
      ],
      "NECK": [
        "Fire DMG",
        "ATK%"
      ],
      "OBJECT": [
        "ATK%"
      ]
    },
    "eidolon": "111201",
    "talents": "14",
    "synergies": [
      "1107",
      "1305",
      "1208",
      "1217",
      "1204",
      "1303",
      "1006",
      "1009"
    ]
  },
  "1203": {
    "name": "Luocha",
    "weapons": [
      "23008",
      "20015",
      "21000"
    ],
    "subStats": [
      "SPD",
      "ATK",
      "HP",
      "DEF",
      "Effect RES",
      "Break Effect"
    ],
    "stats": {
      "BaseSpeed": "143+",
      "CriticalChance": "5%",
      "CriticalDamage": "50%",
      "SPRatio": "119%",
      "StatusProbabilityBase": "0%",
      "BreakDamageAddedRatioBase": "0%",
      "HealRatio": "34.56%",
      "ImaginaryAddedRatio": "0%"
    },
    "version": "2.0",
    "sets": [
      [
        "310",
        "302"
      ],
      [
        "114",
        "101"
      ],
      [
        "102"
      ]
    ],
    "mainStats": {
      "HEAD": "HP",
      "HAND": "ATK",
      "BODY": [
        "OHB%"
      ],
      "FOOT": [
        "SPD"
      ],
      "NECK": [
        "ATK%",
        "HP%",
        "DEF%"
      ],
      "OBJECT": [
        "Energy"
      ]
    },
    "eidolon": "120301",
    "talents": "9",
    "synergies": [
      "1302",
      "1205",
      "1107",
      "1213",
      "1204",
      "1212",
      "1005",
      "1102"
    ]
  },
  "1205": {
    "name": "Blade",
    "weapons": [
      "23009",
      "21012",
      "21038"
    ],
    "subStats": [
      "CRIT DMG",
      "CRIT Rate",
      "HP",
      "SPD",
      "Effect RES"
    ],
    "stats": {
      "BaseSpeed": "134+",
      "CriticalChance": "70%",
      "CriticalDamage": "140%",
      "SPRatio": "100%",
      "StatusProbabilityBase": "0%",
      "BreakDamageAddedRatioBase": "0%"
    },
    "version": "2.3",
    "sets": [
      [
        "306",
        "309"
      ],
      [
        "113"
      ],
      [
        "110",
        "113"
      ]
    ],
    "mainStats": {
      "HEAD": "HP",
      "HAND": "ATK",
      "BODY": [
        "Crit DMG / Rate"
      ],
      "FOOT": [
        "HP%",
        "SPD"
      ],
      "NECK": [
        "HP%",
        "Wind DMG"
      ],
      "OBJECT": [
        "HP%"
      ]
    },
    "eidolon": "120501",
    "talents": "25",
    "synergies": [
      "1101",
      "1217",
      "1314",
      "1212",
      "1203",
      "1303",
      "1006",
      "1106"
    ]
  },
  "1207": {
    "name": "Yukong",
    "weapons": [
      "20012",
      "21004",
      "21011"
    ],
    "subStats": [
      "SPD",
      "HP",
      "DEF",
      "Effect RES"
    ],
    "stats": {
      "BaseSpeed": "107+",
      "CriticalChance": "5%",
      "CriticalDamage": "50%",
      "SPRatio": "119%",
      "StatusProbabilityBase": "0%",
      "BreakDamageAddedRatioBase": "0%"
    },
    "version": "2.0",
    "sets": [
      [
        "310",
        "312"
      ],
      [
        "113",
        "114"
      ],
      [
        "102"
      ]
    ],
    "mainStats": {
      "HEAD": "HP",
      "HAND": "ATK",
      "BODY": [
        "HP%",
        "DEF%"
      ],
      "FOOT": [
        "SPD",
        "HP%",
        "DEF%"
      ],
      "NECK": [
        "HP%",
        "DEF%"
      ],
      "OBJECT": [
        "Energy"
      ]
    },
    "eidolon": "120706",
    "talents": "13",
    "synergies": [
      "1302",
      "1205",
      "1107",
      "1213",
      "1102",
      "1004",
      "1008",
      "1312"
    ]
  },
  "1208": {
    "name": "Fu Xuan",
    "weapons": [
      "23011",
      "21009"
    ],
    "subStats": [
      "SPD",
      "HP",
      "DEF",
      "Effect RES"
    ],
    "stats": {
      "BaseSpeed": "134+",
      "CriticalChance": "5%",
      "CriticalDamage": "50%",
      "SPRatio": "119%",
      "StatusProbabilityBase": "0%",
      "BreakDamageAddedRatioBase": "0%"
    },
    "version": "2.0",
    "sets": [
      [
        "310",
        "302"
      ],
      [
        "106",
        "113"
      ],
      [
        "114",
        "113"
      ]
    ],
    "mainStats": {
      "HEAD": "HP",
      "HAND": "ATK",
      "BODY": [
        "HP%",
        "DEF%"
      ],
      "FOOT": [
        "SPD"
      ],
      "NECK": [
        "HP%",
        "DEF%"
      ],
      "OBJECT": [
        "Energy"
      ]
    },
    "eidolon": "120802",
    "talents": "9",
    "synergies": [
      "1302",
      "1205",
      "1107",
      "1213",
      "1204",
      "1102",
      "1201",
      "1214"
    ]
  },
  "1209": {
    "name": "Yanqing",
    "weapons": [
      "23001",
      "23012",
      "24001"
    ],
    "subStats": [
      "CRIT DMG",
      "CRIT Rate",
      "ATK",
      "SPD"
    ],
    "stats": {
      "BaseSpeed": "134+",
      "CriticalChance": "20%",
      "CriticalDamage": "200%",
      "SPRatio": "100%",
      "StatusProbabilityBase": "0%",
      "BreakDamageAddedRatioBase": "0%"
    },
    "version": "2.2",
    "sets": [
      [
        "311",
        "301"
      ],
      [
        "104"
      ],
      [
        "104",
        "102"
      ]
    ],
    "mainStats": {
      "HEAD": "HP",
      "HAND": "ATK",
      "BODY": [
        "Crit DMG"
      ],
      "FOOT": [
        "SPD"
      ],
      "NECK": [
        "Ice DMG"
      ],
      "OBJECT": [
        "ATK%"
      ]
    },
    "eidolon": "120906",
    "talents": "3",
    "synergies": [
      "1304",
      "1101",
      "1104",
      "1309",
      "1303",
      "1306",
      "1106",
      "1202"
    ]
  },
  "1210": {
    "name": "Guinaifen",
    "weapons": [
      "21001",
      "21008",
      "21015"
    ],
    "subStats": [
      "Effect Hit Rate",
      "ATK",
      "SPD",
      "Break Effect"
    ],
    "stats": {
      "BaseSpeed": "143+",
      "CriticalChance": "5%",
      "CriticalDamage": "50%",
      "SPRatio": "100%",
      "StatusProbabilityBase": "E0: 67%/E1: 43%",
      "BreakDamageAddedRatioBase": "0%"
    },
    "version": "2.3",
    "sets": [
      [
        "311",
        "301"
      ],
      [
        "116"
      ],
      [
        "107",
        "102"
      ]
    ],
    "mainStats": {
      "HEAD": "HP",
      "HAND": "ATK",
      "BODY": [
        "EHR%",
        "ATK%"
      ],
      "FOOT": [
        "SPD"
      ],
      "NECK": [
        "Fire DMG"
      ],
      "OBJECT": [
        "ATK%"
      ]
    },
    "eidolon": "121001",
    "talents": "9",
    "synergies": [
      "1307",
      "1217",
      "1005",
      "1203",
      "1303",
      "1009",
      "1106",
      "1108"
    ]
  },
  "1211": {
    "name": "Bailu",
    "weapons": [
      "23017",
      "23013",
      "20015"
    ],
    "subStats": [
      "SPD",
      "HP",
      "Effect RES",
      "DEF"
    ],
    "stats": {
      "BaseSpeed": "143+",
      "CriticalChance": "5%",
      "CriticalDamage": "50%",
      "SPRatio": "119%",
      "StatusProbabilityBase": "0%",
      "BreakDamageAddedRatioBase": "0%",
      "HealRatio": "34.56%"
    },
    "version": "2.0",
    "sets": [
      [
        "310",
        "302"
      ],
      [
        "114"
      ],
      [
        "101"
      ]
    ],
    "mainStats": {
      "HEAD": "HP",
      "HAND": "ATK",
      "BODY": [
        "OHB%"
      ],
      "FOOT": [
        "SPD"
      ],
      "NECK": [
        "HP%"
      ],
      "OBJECT": [
        "Energy"
      ]
    },
    "eidolon": "121104",
    "talents": "1",
    "synergies": [
      "1302",
      "1205",
      "1107",
      "1204",
      "1212",
      "1005",
      "1102",
      "1103"
    ]
  },
  "1212": {
    "name": "Jingliu",
    "weapons": [
      "23014",
      "24000",
      "21012"
    ],
    "subStats": [
      "CRIT DMG",
      "CRIT Rate",
      "ATK",
      "SPD"
    ],
    "stats": {
      "BaseSpeed": "134+",
      "CriticalChance": "50%",
      "CriticalDamage": "200%",
      "SPRatio": "100%",
      "StatusProbabilityBase": "0%",
      "BreakDamageAddedRatioBase": "0%"
    },
    "version": "2.0",
    "sets": [
      [
        "309",
        "311"
      ],
      [
        "108"
      ],
      [
        "104"
      ]
    ],
    "mainStats": {
      "HEAD": "HP",
      "HAND": "ATK",
      "BODY": [
        "Crit DMG"
      ],
      "FOOT": [
        "SPD",
        "ATK%"
      ],
      "NECK": [
        "Ice DMG"
      ],
      "OBJECT": [
        "ATK%"
      ]
    },
    "eidolon": "121201",
    "talents": "15",
    "synergies": [
      "1211",
      "1101",
      "1208",
      "1217",
      "1203",
      "1303",
      "1106",
      "1202"
    ]
  },
  "1213": {
    "name": "Dan Heng • Imbibitor Lunae",
    "weapons": [
      "23015",
      "24000",
      "21019"
    ],
    "subStats": [
      "CRIT Rate",
      "CRIT DMG",
      "ATK",
      "SPD"
    ],
    "stats": {
      "BaseSpeed": "121/134+",
      "CriticalChance": "70%",
      "CriticalDamage": "140%",
      "SPRatio": "100%",
      "StatusProbabilityBase": "0%",
      "BreakDamageAddedRatioBase": "0%"
    },
    "version": "2.0",
    "sets": [
      [
        "309",
        "311"
      ],
      [
        "112"
      ],
      [
        "102"
      ]
    ],
    "mainStats": {
      "HEAD": "HP",
      "HAND": "ATK",
      "BODY": [
        "Crit DMG / Rate"
      ],
      "FOOT": [
        "SPD",
        "ATK%"
      ],
      "NECK": [
        "Imaginary DMG"
      ],
      "OBJECT": [
        "ATK%"
      ]
    },
    "eidolon": "121302",
    "talents": "23",
    "synergies": [
      "1101",
      "1208",
      "1217",
      "1203",
      "1306",
      "1215",
      "1202",
      "1207"
    ]
  },
  "1214": {
    "name": "Xueyi",
    "weapons": [
      "21042",
      "24000",
      "21019"
    ],
    "subStats": [
      "Break Effect",
      "ATK",
      "CRIT DMG",
      "CRIT Rate",
      "SPD"
    ],
    "stats": {
      "BaseSpeed": "134+",
      "CriticalChance": "70%",
      "CriticalDamage": "140%",
      "SPRatio": "100%",
      "StatusProbabilityBase": "0%",
      "BreakDamageAddedRatioBase": "240%/200%"
    },
    "version": "2.2",
    "sets": [
      [
        "306",
        "311"
      ],
      [
        "108"
      ],
      [
        "111"
      ]
    ],
    "mainStats": {
      "HEAD": "HP",
      "HAND": "ATK",
      "BODY": [
        "Crit DMG / Rate"
      ],
      "FOOT": [
        "SPD"
      ],
      "NECK": [
        "ATK%"
      ],
      "OBJECT": [
        "Break",
        "ATK%"
      ]
    },
    "eidolon": "121406",
    "talents": "1",
    "synergies": [
      "8005",
      "1217",
      "1303",
      "1006",
      "1306",
      "1301",
      "1215",
      "1202"
    ]
  },
  "1215": {
    "name": "Hanya",
    "weapons": [
      "20012",
      "21004",
      "21011"
    ],
    "subStats": [
      "SPD",
      "HP",
      "DEF",
      "Effect RES",
      "Break Effect"
    ],
    "stats": {
      "BaseSpeed": "161",
      "CriticalChance": "5%",
      "CriticalDamage": "50%",
      "SPRatio": "119%",
      "StatusProbabilityBase": "0%",
      "BreakDamageAddedRatioBase": "0%"
    },
    "version": "2.0",
    "sets": [
      [
        "310",
        "312"
      ],
      [
        "114"
      ],
      [
        "113",
        "114"
      ]
    ],
    "mainStats": {
      "HEAD": "HP",
      "HAND": "ATK",
      "BODY": [
        "HP%",
        "DEF%"
      ],
      "FOOT": [
        "SPD"
      ],
      "NECK": [
        "HP%",
        "DEF%"
      ],
      "OBJECT": [
        "Energy"
      ]
    },
    "eidolon": "121504",
    "talents": "1",
    "synergies": [
      "1302",
      "1213",
      "1204",
      "1212",
      "1005",
      "1102",
      "1002",
      "1206"
    ]
  },
  "1217": {
    "name": "Huohuo",
    "weapons": [
      "23017",
      "23013",
      "21000"
    ],
    "subStats": [
      "SPD",
      "HP",
      "Effect RES",
      "DEF"
    ],
    "stats": {
      "BaseSpeed": "143+",
      "CriticalChance": "5%",
      "CriticalDamage": "50%",
      "SPRatio": "119%",
      "StatusProbabilityBase": "0%",
      "BreakDamageAddedRatioBase": "0%",
      "HealRatio": "34.56%"
    },
    "version": "2.0",
    "sets": [
      [
        "310",
        "312"
      ],
      [
        "114"
      ],
      [
        "101"
      ]
    ],
    "mainStats": {
      "HEAD": "HP",
      "HAND": "ATK",
      "BODY": [
        "OHB%"
      ],
      "FOOT": [
        "SPD"
      ],
      "NECK": [
        "HP%"
      ],
      "OBJECT": [
        "Energy"
      ]
    },
    "eidolon": "121701",
    "talents": "1",
    "synergies": [
      "1302",
      "1307",
      "1213",
      "1305",
      "1204",
      "1212",
      "1005",
      "1220"
    ]
  },
  "1218": {
    "name": "Jiaoqiu",
    "weapons": [
      "23029",
      "21008",
      "21015"
    ],
    "subStats": [
      "Effect Hit Rate",
      "SPD",
      "ATK"
    ],
    "stats": {
      "BaseSpeed": "143+",
      "CriticalChance": "5%",
      "CriticalDamage": "50%",
      "SPRatio": "119%",
      "StatusProbabilityBase": "140%+",
      "BreakDamageAddedRatioBase": "0%"
    },
    "version": "2.5",
    "sets": [
      [
        "310",
        "302"
      ],
      [
        "114"
      ],
      [
        "114",
        "102"
      ]
    ],
    "mainStats": {
      "HEAD": "HP",
      "HAND": "ATK",
      "BODY": [
        "EHR%"
      ],
      "FOOT": [
        "SPD"
      ],
      "NECK": [
        "Fire DMG"
      ],
      "OBJECT": [
        "Energy"
      ]
    },
    "eidolon": "121802",
    "talents": "7",
    "synergies": [
      "1308",
      "1304",
      "1307",
      "1305",
      "1208",
      "1006",
      "1306",
      "1106"
    ]
  },
  "1220": {
    "name": "Feixiao",
    "weapons": [
      "23031",
      "23020",
      "23016"
    ],
    "subStats": [
      "SPD",
      "CRIT Rate",
      "CRIT DMG",
      "ATK"
    ],
    "stats": {
      "BaseSpeed": "134",
      "CriticalChance": "70%",
      "CriticalDamage": "140%",
      "SPRatio": "100%",
      "StatusProbabilityBase": "0%",
      "BreakDamageAddedRatioBase": "0%"
    },
    "version": "2.5",
    "sets": [
      [
        "314",
        "306"
      ],
      [
        "120"
      ],
      [
        "115"
      ]
    ],
    "mainStats": {
      "HEAD": "HP",
      "HAND": "ATK",
      "BODY": [
        "Crit DMG / Rate"
      ],
      "FOOT": [
        "ATK%",
        "SPD"
      ],
      "NECK": [
        "Wind DMG",
        "ATK%"
      ],
      "OBJECT": [
        "ATK%"
      ]
    },
    "eidolon": "122002",
    "talents": "1",
    "synergies": [
      "1304",
      "1309",
      "1112",
      "1303",
      "1306",
      "1001",
      "1223",
      "1301"
    ]
  },
  "1221": {
    "name": "Yunli",
    "weapons": [
      "23030",
      "23009",
      "24000"
    ],
    "subStats": [
      "CRIT Rate",
      "CRIT DMG",
      "ATK"
    ],
    "stats": {
      "BaseSpeed": "94",
      "CriticalChance": "70%",
      "CriticalDamage": "140%",
      "SPRatio": "100%",
      "StatusProbabilityBase": "0%",
      "BreakDamageAddedRatioBase": "0%"
    },
    "version": "2.5",
    "sets": [
      [
        "306",
        "315"
      ],
      [
        "120"
      ],
      [
        "115"
      ]
    ],
    "mainStats": {
      "HEAD": "HP",
      "HAND": "ATK",
      "BODY": [
        "Crit DMG / Rate"
      ],
      "FOOT": [
        "ATK%"
      ],
      "NECK": [
        "Physical DMG",
        "ATK%"
      ],
      "OBJECT": [
        "ATK%"
      ]
    },
    "eidolon": "122102",
    "talents": "1",
    "synergies": [
      "1304",
      "1217",
      "1309",
      "1303",
      "1306",
      "1112",
      "1110",
      "1202"
    ]
  },
  "1222": {
    "name": "Lingsha",
    "weapons": [
      "23032",
      "23017",
      "23008"
    ],
    "subStats": [
      "Break Effect",
      "SPD",
      "ATK"
    ],
    "stats": {
      "BaseSpeed": "143+",
      "CriticalChance": "5%",
      "CriticalDamage": "50%",
      "SPRatio": "119%",
      "StatusProbabilityBase": "0%+",
      "BreakDamageAddedRatioBase": "0%",
      "HealRatio": "34.56%"
    },
    "version": "2.5",
    "sets": [
      [
        "316",
        "307"
      ],
      [
        "119"
      ],
      [
        "111"
      ]
    ],
    "mainStats": {
      "HEAD": "HP",
      "HAND": "ATK",
      "BODY": [
        "OHB%"
      ],
      "FOOT": [
        "SPD"
      ],
      "NECK": [
        "ATK%"
      ],
      "OBJECT": [
        "Energy"
      ]
    },
    "eidolon": "122202",
    "talents": "3",
    "synergies": [
      "1315",
      "1220",
      "1310",
      "8005",
      "1309",
      "1303",
      "1001"
    ]
  },
  "1223": {
    "name": "Moze",
    "weapons": [
      "23020",
      "23016",
      "21010"
    ],
    "subStats": [
      "SPD",
      "CRIT Rate",
      "CRIT DMG",
      "ATK"
    ],
    "stats": {
      "BaseSpeed": "134",
      "CriticalChance": "70%",
      "CriticalDamage": "140%",
      "SPRatio": "100%",
      "StatusProbabilityBase": "0%",
      "BreakDamageAddedRatioBase": "0%"
    },
    "version": "2.5",
    "sets": [
      [
        "315",
        "306"
      ],
      [
        "117"
      ],
      [
        "115"
      ]
    ],
    "mainStats": {
      "HEAD": "HP",
      "HAND": "ATK",
      "BODY": [
        "Crit DMG / Rate"
      ],
      "FOOT": [
        "ATK%"
      ],
      "NECK": [
        "Lightning DMG"
      ],
      "OBJECT": [
        "ATK%"
      ]
    },
    "eidolon": "122306",
    "talents": "7",
    "synergies": [
      "1304",
      "1305",
      "1220",
      "1217",
      "1309",
      "1112",
      "1301",
      "1202"
    ]
  },
  "1224": {
    "name": "March 7th (Imaginary)",
    "weapons": [
      "23001",
      "23020",
      "23016"
    ],
    "subStats": [
      "SPD",
      "CRIT Rate",
      "CRIT DMG",
      "ATK"
    ],
    "stats": {
      "BaseSpeed": "134",
      "CriticalChance": "70%",
      "CriticalDamage": "140%",
      "SPRatio": "100%",
      "StatusProbabilityBase": "0%",
      "BreakDamageAddedRatioBase": "0%"
    },
    "version": "2.5",
    "sets": [
      [
        "309",
        "314"
      ],
      [
        "102"
      ],
      [
        "102",
        "112"
      ]
    ],
    "mainStats": {
      "HEAD": "HP",
      "HAND": "ATK",
      "BODY": [
        "Crit DMG / Rate"
      ],
      "FOOT": [
        "SPD",
        "ATK%"
      ],
      "NECK": [
        "Imaginary DMG",
        "ATK%"
      ],
      "OBJECT": [
        "ATK%"
      ]
    },
    "eidolon": "122406",
    "talents": "22",
    "synergies": [
      "1304",
      "1220",
      "8005",
      "1217",
      "1303",
      "1309",
      "1112",
      "1301"
    ]
  },
  "1225": {
    "name": "Fugue",
    "weapons": [
      "23035",
      "23007",
      "21015"
    ],
    "subStats": [
      "SPD",
      "Break Effect",
      "Effect Hit Rate",
      "ATK",
      "HP",
      "DEF"
    ],
    "stats": {
      "BaseSpeed": "161+",
      "CriticalChance": "5%",
      "CriticalDamage": "50%",
      "SPRatio": "100%",
      "StatusProbabilityBase": "67%",
      "BreakDamageAddedRatioBase": "220%",
      "HealRatio": "0%"
    },
    "version": "2.7",
    "sets": [
      [
        "316",
        "307"
      ],
      [
        "119"
      ],
      [
        "119",
        "114"
      ]
    ],
    "mainStats": {
      "HEAD": "HP",
      "HAND": "ATK",
      "BODY": [
        "EHR%"
      ],
      "FOOT": [
        "SPD"
      ],
      "NECK": [
        "HP%",
        "DEF%"
      ],
      "OBJECT": [
        "Break"
      ]
    },
    "eidolon": "122502",
    "talents": "15",
    "synergies": [
      "1308",
      "1310",
      "1003",
      "1222",
      "1317",
      "1301",
      "1013",
      "1224"
    ]
  },
  "1301": {
    "name": "Gallagher",
    "weapons": [
      "23017",
      "21035",
      "20015"
    ],
    "subStats": [
      "Break Effect",
      "SPD",
      "HP",
      "DEF",
      "Effect RES"
    ],
    "stats": {
      "BaseSpeed": "134+/161",
      "CriticalChance": "5%",
      "CriticalDamage": "50%",
      "SPRatio": "119%",
      "StatusProbabilityBase": "0%",
      "BreakDamageAddedRatioBase": "150%",
      "HealRatio": "34.56%"
    },
    "version": "2.2",
    "sets": [
      [
        "310",
        "302"
      ],
      [
        "118",
        "114"
      ],
      [
        "101"
      ]
    ],
    "mainStats": {
      "HEAD": "HP",
      "HAND": "ATK",
      "BODY": [
        "OHB%"
      ],
      "FOOT": [
        "SPD"
      ],
      "NECK": [
        "HP%",
        "DEF%"
      ],
      "OBJECT": [
        "Energy"
      ]
    },
    "eidolon": "130106",
    "talents": "15",
    "synergies": [
      "1308",
      "1315",
      "1305",
      "8005",
      "1303",
      "1006",
      "1111",
      "1214"
    ]
  },
  "1302": {
    "name": "Argenti",
    "weapons": [
      "23018",
      "21034",
      "23000"
    ],
    "subStats": [
      "SPD",
      "CRIT DMG",
      "CRIT Rate",
      "ATK"
    ],
    "stats": {
      "BaseSpeed": "134+",
      "CriticalChance": "70%",
      "CriticalDamage": "140%",
      "SPRatio": "100%",
      "StatusProbabilityBase": "0%",
      "BreakDamageAddedRatioBase": "0%"
    },
    "version": "2.3",
    "sets": [
      [
        "311",
        "306"
      ],
      [
        "105"
      ],
      [
        "102"
      ]
    ],
    "mainStats": {
      "HEAD": "HP",
      "HAND": "ATK",
      "BODY": [
        "Crit DMG / Rate"
      ],
      "FOOT": [
        "SPD"
      ],
      "NECK": [
        "Physical DMG"
      ],
      "OBJECT": [
        "ATK%"
      ]
    },
    "eidolon": "130202",
    "talents": "3",
    "synergies": [
      "1303",
      "1101",
      "1208",
      "1217",
      "1306",
      "1215",
      "1106",
      "1202"
    ]
  },
  "1303": {
    "name": "Ruan Mei",
    "weapons": [
      "23019",
      "21004",
      "20012"
    ],
    "subStats": [
      "Break Effect",
      "SPD",
      "HP",
      "DEF",
      "Effect RES"
    ],
    "stats": {
      "BaseSpeed": "134+",
      "CriticalChance": "5%",
      "CriticalDamage": "50%",
      "SPRatio": "119%",
      "StatusProbabilityBase": "0%",
      "BreakDamageAddedRatioBase": "180%"
    },
    "version": "2.3",
    "sets": [
      [
        "312",
        "308"
      ],
      [
        "118"
      ],
      [
        "114",
        "118"
      ]
    ],
    "mainStats": {
      "HEAD": "HP",
      "HAND": "ATK",
      "BODY": [
        "HP%",
        "DEF%"
      ],
      "FOOT": [
        "SPD"
      ],
      "NECK": [
        "HP%",
        "DEF%"
      ],
      "OBJECT": [
        "Energy"
      ]
    },
    "eidolon": "130301",
    "talents": "1",
    "synergies": [
      "1308",
      "1304",
      "1205",
      "1315",
      "1310",
      "8005",
      "1212",
      "1005"
    ]
  },
  "1304": {
    "name": "Aventurine",
    "weapons": [
      "23023",
      "23005",
      "21043"
    ],
    "subStats": [
      "DEF",
      "SPD",
      "CRIT DMG",
      "CRIT Rate",
      "Effect RES"
    ],
    "stats": {
      "BaseSpeed": "106/134+",
      "CriticalChance": "70%",
      "CriticalDamage": "140%",
      "SPRatio": "100%",
      "StatusProbabilityBase": "0%"
    },
    "version": "2.3",
    "sets": [
      [
        "306",
        "310"
      ],
      [
        "103"
      ],
      [
        "103",
        "115"
      ]
    ],
    "mainStats": {
      "HEAD": "HP",
      "HAND": "ATK",
      "BODY": [
        "Crit DMG / Rate",
        "DEF%"
      ],
      "FOOT": [
        "DEF%",
        "SPD"
      ],
      "NECK": [
        "DEF%",
        "Imaginary DMG"
      ],
      "OBJECT": [
        "DEF%"
      ]
    },
    "eidolon": "130401",
    "talents": "15",
    "synergies": [
      "1308",
      "1107",
      "1305",
      "1005",
      "1309",
      "1303",
      "1112",
      "1106"
    ]
  },
  "1305": {
    "name": "Dr. Ratio",
    "weapons": [
      "23020",
      "23016",
      "24001"
    ],
    "subStats": [
      "CRIT DMG",
      "CRIT Rate",
      "ATK",
      "SPD"
    ],
    "stats": {
      "BaseSpeed": "134+",
      "CriticalChance": "70%",
      "CriticalDamage": "140%",
      "SPRatio": "100%",
      "StatusProbabilityBase": "0%",
      "BreakDamageAddedRatioBase": "0%"
    },
    "version": "2.2",
    "sets": [
      [
        "306",
        "311"
      ],
      [
        "117"
      ],
      [
        "112"
      ]
    ],
    "mainStats": {
      "HEAD": "HP",
      "HAND": "ATK",
      "BODY": [
        "Crit DMG / Rate"
      ],
      "FOOT": [
        "SPD"
      ],
      "NECK": [
        "ATK%",
        "Imaginary DMG"
      ],
      "OBJECT": [
        "ATK%"
      ]
    },
    "eidolon": "130506",
    "talents": "7",
    "synergies": [
      "1304",
      "1309",
      "1303",
      "1006",
      "1306",
      "1112",
      "1106",
      "1202"
    ]
  },
  "1306": {
    "name": "Sparkle",
    "weapons": [
      "23021",
      "21011",
      "23003"
    ],
    "subStats": [
      "CRIT DMG",
      "SPD",
      "HP",
      "DEF",
      "Effect RES"
    ],
    "stats": {
      "BaseSpeed": "134/161",
      "CriticalChance": "5%",
      "CriticalDamage": "200%",
      "SPRatio": "119%",
      "StatusProbabilityBase": "0%",
      "BreakDamageAddedRatioBase": "0%"
    },
    "version": "2.0",
    "sets": [
      [
        "310",
        "302"
      ],
      [
        "113",
        "114"
      ],
      [
        "114"
      ]
    ],
    "mainStats": {
      "HEAD": "HP",
      "HAND": "ATK",
      "BODY": [
        "Crit DMG"
      ],
      "FOOT": [
        "SPD"
      ],
      "NECK": [
        "HP%",
        "DEF%"
      ],
      "OBJECT": [
        "Energy"
      ]
    },
    "eidolon": "130602",
    "talents": "3",
    "synergies": [
      "1302",
      "1213",
      "1305",
      "1204",
      "1102",
      "1112",
      "1201",
      "1214"
    ]
  },
  "1307": {
    "name": "Black Swan",
    "weapons": [
      "23022",
      "21008",
      "21001"
    ],
    "subStats": [
      "Effect Hit Rate",
      "SPD",
      "ATK"
    ],
    "stats": {
      "BaseSpeed": "120+",
      "CriticalChance": "5%",
      "CriticalDamage": "50%",
      "SPRatio": "100%",
      "StatusProbabilityBase": "120%",
      "BreakDamageAddedRatioBase": "0%"
    },
    "version": "2.3",
    "sets": [
      [
        "303",
        "311"
      ],
      [
        "116"
      ],
      [
        "117",
        "116"
      ]
    ],
    "mainStats": {
      "HEAD": "HP",
      "HAND": "ATK",
      "BODY": [
        "ATK%",
        "EHR%"
      ],
      "FOOT": [
        "SPD"
      ],
      "NECK": [
        "ATK%",
        "Wind DMG"
      ],
      "OBJECT": [
        "ATK%"
      ]
    },
    "eidolon": "130701",
    "talents": "7",
    "synergies": [
      "1308",
      "1217",
      "1005",
      "1309",
      "1303",
      "1009",
      "1210",
      "1108"
    ]
  },
  "1308": {
    "name": "Acheron",
    "weapons": [
      "23024",
      "23007",
      "21001",
      "21044"
    ],
    "subStats": [
      "CRIT DMG",
      "CRIT Rate",
      "ATK",
      "SPD"
    ],
    "stats": {
      "BaseSpeed": "101/134+",
      "CriticalChance": "70%",
      "CriticalDamage": "140%",
      "SPRatio": "100%",
      "StatusProbabilityBase": "0%",
      "BreakDamageAddedRatioBase": "0%"
    },
    "version": "2.3",
    "sets": [
      [
        "314",
        "306"
      ],
      [
        "117"
      ],
      [
        "109"
      ]
    ],
    "mainStats": {
      "HEAD": "HP",
      "HAND": "ATK",
      "BODY": [
        "Crit DMG / Rate"
      ],
      "FOOT": [
        "ATK%",
        "SPD"
      ],
      "NECK": [
        "ATK%",
        "Lightning DMG"
      ],
      "OBJECT": [
        "ATK%"
      ]
    },
    "eidolon": "130802",
    "talents": "1",
    "synergies": [
      "1304",
      "1104",
      "1006",
      "1306",
      "1004",
      "1307",
      "1301",
      "1106",
      "1210"
    ]
  },
  "1309": {
    "weapons": [
      "23026",
      "22002",
      "23003"
    ],
    "subStats": [
      "ATK",
      "SPD",
      "HP",
      "DEF",
      "Effect RES"
    ],
    "stats": {
      "BaseSpeed": "145+",
      "CriticalChance": "5%",
      "CriticalDamage": "50%",
      "SPRatio": "119%",
      "StatusProbabilityBase": "0%",
      "BreakDamageAddedRatioBase": "150%"
    },
    "sets": [
      [
        "308",
        "312"
      ],
      [
        "102",
        "116"
      ],
      [
        "102"
      ]
    ],
    "mainStats": {
      "HEAD": "HP",
      "HAND": "ATK",
      "BODY": [
        "ATK%"
      ],
      "FOOT": [
        "ATK%",
        "SPD"
      ],
      "NECK": [
        "ATK%"
      ],
      "OBJECT": [
        "Energy"
      ]
    },
    "eidolon": "130902",
    "talents": "13",
    "synergies": [
      "1304",
      "1315",
      "1107",
      "1305",
      "1003",
      "1204",
      "1112",
      "1013"
    ]
  },
  "1310": {
    "name": "Firefly",
    "weapons": [
      "23025",
      "24000",
      "21042"
    ],
    "subStats": [
      "SPD",
      "Break Effect",
      "ATK"
    ],
    "stats": {
      "BaseSpeed": "165+",
      "CriticalChance": "5%",
      "CriticalDamage": "50%",
      "SPRatio": "100%",
      "StatusProbabilityBase": "0%",
      "BreakDamageAddedRatioBase": "360%"
    },
    "version": "2.3",
    "sets": [
      [
        "316",
        "307"
      ],
      [
        "119"
      ],
      [
        "111"
      ]
    ],
    "mainStats": {
      "HEAD": "HP",
      "HAND": "ATK",
      "BODY": [
        "ATK%"
      ],
      "FOOT": [
        "SPD"
      ],
      "NECK": [
        "ATK%"
      ],
      "OBJECT": [
        "Break"
      ]
    },
    "eidolon": "131001",
    "talents": "3",
    "synergies": [
      "1208",
      "1217",
      "1203",
      "8005",
      "1303",
      "1006",
      "1009",
      "1301"
    ]
  },
  "1312": {
    "name": "Misha",
    "weapons": [
      "24000",
      "21012",
      "21019"
    ],
    "subStats": [
      "CRIT DMG",
      "CRIT Rate",
      "ATK",
      "SPD"
    ],
    "stats": {
      "BaseSpeed": "134+",
      "CriticalChance": "70%",
      "CriticalDamage": "140%",
      "SPRatio": "100%",
      "StatusProbabilityBase": "0%",
      "BreakDamageAddedRatioBase": "0%"
    },
    "version": "2.0",
    "sets": [
      [
        "306",
        "311"
      ],
      [
        "104"
      ],
      [
        "104",
        "102"
      ]
    ],
    "mainStats": {
      "HEAD": "HP",
      "HAND": "ATK",
      "BODY": [
        "Crit DMG / Rate"
      ],
      "FOOT": [
        "SPD"
      ],
      "NECK": [
        "Ice DMG"
      ],
      "OBJECT": [
        "ATK%"
      ]
    },
    "eidolon": "131204",
    "talents": "3",
    "synergies": [
      "1101",
      "1208",
      "1217",
      "1203",
      "1303",
      "1306",
      "1106",
      "1202"
    ]
  },
  "1313": {
    "name": "Sunday",
    "weapons": [
      "23034",
      "23003",
      "21025"
    ],
    "subStats": [
      "SPD",
      "CRIT DMG",
      "Effect RES",
      "DEF",
      "HP"
    ],
    "stats": {
      "BaseSpeed": "160+",
      "CriticalChance": "5%",
      "CriticalDamage": "180%+",
      "SPRatio": "119%",
      "StatusProbabilityBase": "0%",
      "BreakDamageAddedRatioBase": "0%"
    },
    "talents": "13",
    "eidolon": "131301",
    "version": "2.7",
    "sets": [
      [
        "317"
      ],
      [
        "121"
      ],
      [
        "121",
        "114"
      ]
    ],
    "mainStats": {
      "HEAD": "HP",
      "HAND": "ATK",
      "BODY": [
        "Crit DMG"
      ],
      "FOOT": [
        "SPD"
      ],
      "NECK": [
        "HP%",
        "DEF%"
      ],
      "OBJECT": [
        "Energy"
      ]
    },
    "synergies": [
      "1304",
      "1205",
      "1107",
      "1003",
      "1309",
      "1303",
      "1112",
      "1013"
    ]
  },
  "1314": {
    "name": "Jade",
    "weapons": [
      "23028",
      "23010",
      "21040"
    ],
    "subStats": [
      "CRIT DMG",
      "CRIT Rate",
      "ATK"
    ],
    "stats": {
      "BaseSpeed": "102",
      "CriticalChance": "70%",
      "CriticalDamage": "140%",
      "SPRatio": "100%",
      "StatusProbabilityBase": "0%",
      "BreakDamageAddedRatioBase": "0%"
    },
    "version": "2.2",
    "sets": [
      [
        "315",
        "306"
      ],
      [
        "108"
      ],
      [
        "120"
      ]
    ],
    "mainStats": {
      "HEAD": "HP",
      "HAND": "ATK",
      "BODY": [
        "Crit DMG / Rate"
      ],
      "FOOT": [
        "ATK%"
      ],
      "NECK": [
        "Quantum DMG"
      ],
      "OBJECT": [
        "ATK%"
      ]
    },
    "eidolon": "131401",
    "talents": "7",
    "synergies": [
      "1304",
      "1205",
      "1107",
      "1003",
      "1309",
      "1303",
      "1112",
      "1013"
    ]
  },
  "1315": {
    "name": "Boothill",
    "weapons": [
      "23027",
      "20014",
      "24001"
    ],
    "subStats": [
      "SPD",
      "Break Effect",
      "CRIT Rate",
      "CRIT DMG",
      "ATK"
    ],
    "stats": {
      "BaseSpeed": "145+",
      "CriticalChance": "60%",
      "CriticalDamage": "120%",
      "SPRatio": "100%",
      "StatusProbabilityBase": "0%"
    },
    "version": "2.3",
    "sets": [
      [
        "307",
        "311"
      ],
      [
        "119"
      ],
      [
        "111"
      ]
    ],
    "mainStats": {
      "HEAD": "HP",
      "HAND": "ATK",
      "BODY": [
        "Crit DMG / Rate"
      ],
      "FOOT": [
        "SPD"
      ],
      "NECK": [
        "Physical DMG",
        "ATK%"
      ],
      "OBJECT": [
        "Break"
      ]
    },
    "eidolon": "131506",
    "talents": "9",
    "synergies": [
      "1309",
      "1304",
      "1101",
      "8005",
      "1303",
      "1006",
      "1301",
      "1106"
    ]
  },
  "1317": {
    "name": "Rappa",
    "weapons": [
      "23033",
      "21045",
      "24004",
      "21013"
    ],
    "subStats": [
      "SPD",
      "Break Effect",
      "ATK"
    ],
    "stats": {
      "BaseSpeed": "145+",
      "CriticalChance": "5%",
      "CriticalDamage": "50%",
      "SPRatio": "100%",
      "StatusProbabilityBase": "0%",
      "BreakDamageAddedRatioBase": "160%/240%",
      "HealRatio": "0%"
    },
    "version": "2.6",
    "sets": [
      [
        "307",
        "316"
      ],
      [
        "119"
      ],
      [
        "111"
      ]
    ],
    "mainStats": {
      "HEAD": "HP",
      "HAND": "ATK",
      "BODY": [
        "ATK%"
      ],
      "FOOT": [
        "SPD"
      ],
      "NECK": [
        "ATK%"
      ],
      "OBJECT": [
        "Break",
        "Energy"
      ]
    },
    "eidolon": "131702",
    "talents": "8",
    "synergies": [
      "8005",
      "1222",
      "1303",
      "1009",
      "1301",
      "1106"
    ]
  },
  "8001": {
    "name": "Destruction Caelus",
    "weapons": [
      "23009",
      "24000",
      "21012"
    ],
    "subStats": [
      "CRIT DMG",
      "CRIT Rate",
      "ATK",
      "SPD"
    ],
    "stats": {
      "BaseSpeed": "134+",
      "CriticalChance": "70%",
      "CriticalDamage": "140%",
      "SPRatio": "100%",
      "StatusProbabilityBase": "0%",
      "BreakDamageAddedRatioBase": "0%"
    },
    "version": "2.0",
    "sets": [
      [
        "309",
        "311"
      ],
      [
        "105"
      ],
      [
        "105",
        "102"
      ]
    ],
    "mainStats": {
      "HEAD": "HP",
      "HAND": "ATK",
      "BODY": [
        "Crit DMG / Rate"
      ],
      "FOOT": [
        "SPD",
        "ATK%"
      ],
      "NECK": [
        "Physical DMG"
      ],
      "OBJECT": [
        "ATK%"
      ]
    },
    "eidolon": "800106",
    "talents": "3",
    "synergies": [
      "1101",
      "1208",
      "1217",
      "1203",
      "1303",
      "1006",
      "1306",
      "1215"
    ]
  },
  "8002": {
    "name": "Destruction Stelle",
    "weapons": [
      "23009",
      "24000",
      "21012"
    ],
    "subStats": [
      "CRIT DMG",
      "CRIT Rate",
      "ATK",
      "SPD"
    ],
    "stats": {
      "BaseSpeed": "134+",
      "CriticalChance": "70%",
      "CriticalDamage": "140%",
      "SPRatio": "100%",
      "StatusProbabilityBase": "0%",
      "BreakDamageAddedRatioBase": "0%"
    },
    "version": "2.0",
    "sets": [
      [
        "309",
        "311"
      ],
      [
        "105"
      ],
      [
        "105",
        "102"
      ]
    ],
    "mainStats": {
      "HEAD": "HP",
      "HAND": "ATK",
      "BODY": [
        "Crit DMG / Rate"
      ],
      "FOOT": [
        "SPD",
        "ATK%"
      ],
      "NECK": [
        "Physical DMG"
      ],
      "OBJECT": [
        "ATK%"
      ]
    },
    "eidolon": "800206",
    "talents": "3",
    "synergies": [
      "1101",
      "1208",
      "1217",
      "1203",
      "1303",
      "1006",
      "1306",
      "1215"
    ]
  },
  "8003": {
    "name": "Preservation Caelus",
    "weapons": [
      "23005",
      "21009",
      "24002"
    ],
    "subStats": [
      "SPD",
      "DEF",
      "Effect RES",
      "HP",
      "Break Effect"
    ],
    "stats": {
      "BaseSpeed": "134+",
      "CriticalChance": "5%",
      "CriticalDamage": "50%",
      "SPRatio": "119%",
      "StatusProbabilityBase": "0%",
      "BreakDamageAddedRatioBase": "0%"
    },
    "version": "2.0",
    "sets": [
      [
        "310",
        "302"
      ],
      [
        "103"
      ],
      [
        "103",
        "106"
      ]
    ],
    "mainStats": {
      "HEAD": "HP",
      "HAND": "ATK",
      "BODY": [
        "DEF%"
      ],
      "FOOT": [
        "SPD"
      ],
      "NECK": [
        "DEF%"
      ],
      "OBJECT": [
        "Energy"
      ]
    },
    "eidolon": "800306",
    "talents": "1",
    "synergies": [
      "1302",
      "1213",
      "1003",
      "1204",
      "1212",
      "1005",
      "1102",
      "1112"
    ]
  },
  "8004": {
    "name": "Preservation Stelle",
    "weapons": [
      "23005",
      "21009",
      "24002"
    ],
    "subStats": [
      "SPD",
      "DEF",
      "Effect RES",
      "HP",
      "Break Effect"
    ],
    "stats": {
      "BaseSpeed": "134+",
      "CriticalChance": "5%",
      "CriticalDamage": "50%",
      "SPRatio": "119%",
      "StatusProbabilityBase": "0%",
      "BreakDamageAddedRatioBase": "0%"
    },
    "version": "2.0",
    "sets": [
      [
        "310",
        "302"
      ],
      [
        "103"
      ],
      [
        "103",
        "106"
      ]
    ],
    "mainStats": {
      "HEAD": "HP",
      "HAND": "ATK",
      "BODY": [
        "DEF%"
      ],
      "FOOT": [
        "SPD"
      ],
      "NECK": [
        "DEF%"
      ],
      "OBJECT": [
        "Energy"
      ]
    },
    "eidolon": "800406",
    "talents": "1",
    "synergies": [
      "1302",
      "1213",
      "1003",
      "1204",
      "1212",
      "1005",
      "1102",
      "1112"
    ]
  },
  "8005": {
    "name": "Harmony Caelus",
    "weapons": [
      "23019",
      "21004",
      "21018"
    ],
    "subStats": [
      "Break Effect",
      "SPD",
      "HP",
      "DEF",
      "Effect RES"
    ],
    "stats": {
      "BaseSpeed": "145+",
      "CriticalChance": "5%",
      "CriticalDamage": "50%",
      "SPRatio": "119%",
      "StatusProbabilityBase": "0%",
      "BreakDamageAddedRatioBase": "200%"
    },
    "version": "2.2",
    "sets": [
      [
        "307"
      ],
      [
        "118"
      ],
      [
        "111"
      ]
    ],
    "mainStats": {
      "HEAD": "HP",
      "HAND": "ATK",
      "BODY": [
        "HP%",
        "DEF%"
      ],
      "FOOT": [
        "SPD"
      ],
      "NECK": [
        "HP%",
        "DEF%"
      ],
      "OBJECT": [
        "Energy"
      ]
    },
    "eidolon": "800506",
    "talents": "1",
    "synergies": [
      "1315",
      "1303",
      "1006",
      "1301",
      "1111",
      "1106",
      "1206",
      "1214"
    ]
  },
  "8006": {
    "name": "Harmony Stelle",
    "weapons": [
      "23019",
      "21004",
      "21018"
    ],
    "subStats": [
      "Break Effect",
      "SPD",
      "HP",
      "DEF",
      "Effect RES"
    ],
    "stats": {
      "BaseSpeed": "145+",
      "CriticalChance": "5%",
      "CriticalDamage": "50%",
      "SPRatio": "119%",
      "StatusProbabilityBase": "0%",
      "BreakDamageAddedRatioBase": "200%"
    },
    "version": "2.3",
    "sets": [
      [
        "307"
      ],
      [
        "118"
      ],
      [
        "111"
      ]
    ],
    "mainStats": {
      "HEAD": "HP",
      "HAND": "ATK",
      "BODY": [
        "HP%",
        "DEF%"
      ],
      "FOOT": [
        "SPD"
      ],
      "NECK": [
        "HP%",
        "DEF%"
      ],
      "OBJECT": [
        "Energy"
      ]
    },
    "eidolon": "800606",
    "talents": "1",
    "synergies": [
      "1315",
      "1303",
      "1006",
      "1301",
      "1111",
      "1106",
      "1206",
      "1214"
    ]
  }
}